len_sentence/__init__.py
len_sentence/count.py
len_sentence/lang_list.py
len_sentence-0.1.1.dist-info/licenses/LICENSE
len_sentence-0.1.1.dist-info/METADATA
len_sentence-0.1.1.dist-info/WHEEL
len_sentence-0.1.1.dist-info/top_level.txt
len_sentence-0.1.1.dist-info/RECORD
