Metadata-Version: 2.4
Name: len-sentence
Version: 0.1.1
Summary: Length of sentence utilities for counting the number of words/characters in a sentence
Author: JackyHe398
Author-email: hekinghung@gmail.com
Requires-Python: >=3.6
License-File: LICENSE
Dynamic: author
Dynamic: author-email
Dynamic: description
Dynamic: description-content-type
Dynamic: license-file
Dynamic: requires-python
Dynamic: summary
